frash/__init__.py
frash/__main__.py
frash/util.py
frash-0.0.8.dist-info/LICENSE
frash-0.0.8.dist-info/METADATA
frash-0.0.8.dist-info/WHEEL
frash-0.0.8.dist-info/entry_points.txt
frash-0.0.8.dist-info/top_level.txt
frash-0.0.8.dist-info/RECORD
