Metadata-Version: 2.1
Name: frash
Version: 0.0.8
Summary: Juggling with hex numbers. Convert integers and floats to hex.
Home-page: https://github.com/0xflotus/frash
Author: 0xflotus
Author-email: 0xflotus+pypi@gmail.com
License: MIT
Platform: UNKNOWN
Classifier: Development Status :: 4 - Beta
Classifier: Intended Audience :: Developers
Classifier: License :: OSI Approved :: MIT License
Classifier: Programming Language :: Python :: 3
Classifier: Programming Language :: Python :: 3.9
Classifier: Topic :: Software Development :: Libraries 
License-File: LICENSE
Requires-Dist: argparse
